aiocontextvars.py
aiocontextvars-0.2.1.dist-info/AUTHORS.rst
aiocontextvars-0.2.1.dist-info/LICENSE
aiocontextvars-0.2.1.dist-info/METADATA
aiocontextvars-0.2.1.dist-info/WHEEL
aiocontextvars-0.2.1.dist-info/top_level.txt
aiocontextvars-0.2.1.dist-info/RECORD
