Metadata-Version: 2.1
Name: aiocontextvars
Version: 0.2.1
Summary: Asyncio support for PEP-567 contextvars backport.
Home-page: https://github.com/fantix/aiocontextvars
Author: Fantix King
Author-email: fantix.king@gmail.com
License: BSD license
Keywords: aiocontextvars
Platform: UNKNOWN
Classifier: Development Status :: 4 - Beta
Classifier: Intended Audience :: Developers
Classifier: License :: OSI Approved :: BSD License
Classifier: Natural Language :: English
Classifier: Programming Language :: Python :: 3
Classifier: Programming Language :: Python :: 3.5
Classifier: Programming Language :: Python :: 3.6
Requires-Python: >=3.5
Requires-Dist: contextvars (==2.3); python_version < "3.7"
